odata_request_parser/__init__.py
odata_request_parser/main.py
odata_request_parser-0.2.dist-info/LICENSE
odata_request_parser-0.2.dist-info/METADATA
odata_request_parser-0.2.dist-info/WHEEL
odata_request_parser-0.2.dist-info/top_level.txt
odata_request_parser-0.2.dist-info/RECORD
