Metadata-Version: 2.1
Name: odata-request-parser
Version: 0.2
Summary: A parser for oData request query strings
Author-email: Jeroen Beekman <j.beekman@amsterdam.nl>
License: Copyright 2022 Gemeente Amsterdam        
Project-URL: Homepage, https://github.com/Amsterdam/odata_request_parser
Project-URL: Bug Tracker, https://github.com/Amsterdam/odata_request_parser/issues
Classifier: Programming Language :: Python :: 3
Classifier: License :: OSI Approved :: MIT License
Classifier: Operating System :: OS Independent
Requires-Python: >=3.9
License-File: LICENSE
